stickybar.py
stickybar-1.0.dist-info/LICENSE
stickybar-1.0.dist-info/METADATA
stickybar-1.0.dist-info/WHEEL
stickybar-1.0.dist-info/top_level.txt
stickybar-1.0.dist-info/RECORD
