Metadata-Version: 2.1
Name: stickybar
Version: 1.0
Summary: Stdout wrapper that prints a status bar below the cursor
Home-page: https://github.com/evalf/stickybar
Author: Evalf
Author-email: info@evalf.com
License: MIT
Platform: UNKNOWN
Requires-Python: >=3.5
Provides-Extra: test
Requires-Dist: pyte ; extra == 'test'
